pollination/appendix_g_performance/__init__.py
pollination/appendix_g_performance/entry.py
pollination_appendix_g_performance-0.3.7.dist-info/LICENSE
pollination_appendix_g_performance-0.3.7.dist-info/METADATA
pollination_appendix_g_performance-0.3.7.dist-info/WHEEL
pollination_appendix_g_performance-0.3.7.dist-info/top_level.txt
pollination_appendix_g_performance-0.3.7.dist-info/RECORD
