Metadata-Version: 2.1
Name: pollination-appendix-g-performance
Version: 0.3.7
Summary: Run an ASHRAE 90.1 Appendix G simulation and compute the Performance Cost Index (PCI) as well as LEED energy points.
Home-page: https://github.com/pollination/appendix-g-performance
Author: pollination
Author-email: info@ladybug.tools
Maintainer: chris, ladybug-tools
Maintainer-email: chris@ladybug.tools, info@ladybug.tools
License: PolyForm Shield License 1.0.0, https://polyformproject.org/wp-content/uploads/2020/06/PolyForm-Shield-1.0.0.txt
Project-URL: icon, https://raw.githubusercontent.com/ladybug-tools/artwork/master/icons_components/honeybee/png/appendixg.png
Project-URL: docker, https://hub.docker.com/r/ladybugtools/honeybee-energy
Keywords: honeybee,energy,ladybug-tools,energyplus,openstudio,energy,appendix-g-performance
License-File: LICENSE
Requires-Dist: pollination-honeybee-energy>=0.7.13
Requires-Dist: pollination-alias>=0.11.8
